igv_jupyterlab/__init__.py
igv_jupyterlab/_frontend.py
igv_jupyterlab/_version.py
igv_jupyterlab/igv_widget.py
igv_jupyterlab/labextension/package.json
igv_jupyterlab/labextension/static/480.096c0f292ca08b40d0f0.js
igv_jupyterlab/labextension/static/480.2e64446bd9326c03cfc8.js
igv_jupyterlab/labextension/static/568.650f80462023cea59569.js
igv_jupyterlab/labextension/static/568.ce6ae4733765ae476e02.js
igv_jupyterlab/labextension/static/897.212108d7a9f6dd83d463.js
igv_jupyterlab/labextension/static/897.212108d7a9f6dd83d463.js.LICENSE.txt
igv_jupyterlab/labextension/static/remoteEntry.165507388bc2744f6a59.js
igv_jupyterlab/labextension/static/remoteEntry.c116e6a32293da1f7ade.js
igv_jupyterlab/labextension/static/style.js
igv_jupyterlab/nbextension/extension.js
igv_jupyterlab/nbextension/index.js
igv_jupyterlab/nbextension/index.js.LICENSE.txt
igv_jupyterlab/nbextension/index.js.map
igv_jupyterlab/tests/__init__.py
igv_jupyterlab/tests/conftest.py
igv_jupyterlab/tests/test_igv.py
igv_jupyterlab/tests/test_nbextension_path.py
igv_jupyterlab-1.0.1.data/data/etc/jupyter/nbconfig/notebook.d/igv_jupyterlab.json
igv_jupyterlab-1.0.1.data/data/share/jupyter/labextensions/@epi2melabs/igv-jupyterlab/install.json
igv_jupyterlab-1.0.1.data/data/share/jupyter/labextensions/@epi2melabs/igv-jupyterlab/package.json
igv_jupyterlab-1.0.1.data/data/share/jupyter/labextensions/@epi2melabs/igv-jupyterlab/static/480.2e64446bd9326c03cfc8.js
igv_jupyterlab-1.0.1.data/data/share/jupyter/labextensions/@epi2melabs/igv-jupyterlab/static/568.650f80462023cea59569.js
igv_jupyterlab-1.0.1.data/data/share/jupyter/labextensions/@epi2melabs/igv-jupyterlab/static/897.212108d7a9f6dd83d463.js
igv_jupyterlab-1.0.1.data/data/share/jupyter/labextensions/@epi2melabs/igv-jupyterlab/static/897.212108d7a9f6dd83d463.js.LICENSE.txt
igv_jupyterlab-1.0.1.data/data/share/jupyter/labextensions/@epi2melabs/igv-jupyterlab/static/remoteEntry.165507388bc2744f6a59.js
igv_jupyterlab-1.0.1.dist-info/LICENSE.txt
igv_jupyterlab-1.0.1.dist-info/METADATA
igv_jupyterlab-1.0.1.dist-info/WHEEL
igv_jupyterlab-1.0.1.dist-info/top_level.txt
igv_jupyterlab-1.0.1.dist-info/RECORD
